tests/__init__.py
tests/common.py
tests/test_composition.py
tests/test_coordination_events.py
tests/test_core.py
tests/test_deterministic_events.py
tests/test_models.py
tests/test_random_events.py
tests/test_util.py
time_blender/__init__.py
time_blender/cli.py
time_blender/config.py
time_blender/coordination_events.py
time_blender/core.py
time_blender/deterministic_events.py
time_blender/models.py
time_blender/random_events.py
time_blender/util.py
time_blender-0.3.0.data/scripts/time_blender
time_blender-0.3.0.dist-info/LICENSE
time_blender-0.3.0.dist-info/METADATA
time_blender-0.3.0.dist-info/WHEEL
time_blender-0.3.0.dist-info/top_level.txt
time_blender-0.3.0.dist-info/RECORD
